{
  "db_name": "PostgreSQL",
  "query": "\n            SELECT COUNT(*) as count\n            FROM workdays\n            WHERE date BETWEEN $1 AND $2\n            AND fk_driver_id = $3\n            ",
  "describe": {
    "columns": [
      {
        "ordinal": 0,
        "name": "count",
        "type_info": "Int8"
      }
    ],
    "parameters": {
      "Left": [
        "Date",
        "Date",
        "Uuid"
      ]
    },
    "nullable": [
      null
    ]
  },
  "hash": "fb1a74f931d0f82221703e6c89526f485d718e60c7238ad79978667d58c24785"
}
